<?xml version="1.0" encoding="UTF-8"?>

<typeSystemDescription xmlns="http://uima.apache.org/resourceSpecifier">
  <name>tf</name>
  <description/>
  <version>1.0</version>
  <vendor/>
  <imports>
    <!-- THESE IMPORTS WILL BE AUTOMATICALLY GENERATED BY A SCRIPT -->
  </imports>
  <types>
    <typeDescription>
      <name>rs.tf.Pose</name>
      <description>TF</description>
      <supertypeName>uima.cas.TOP</supertypeName>
      <features>
        <featureDescription>
          <name>rotation</name>
          <description>3x3 rotation (bullet) matrix</description>
          <rangeTypeName>uima.cas.DoubleArray</rangeTypeName>
          <multipleReferencesAllowed>true</multipleReferencesAllowed>
        </featureDescription>
        <featureDescription>
          <name>translation</name>
          <description/>
          <rangeTypeName>uima.cas.DoubleArray</rangeTypeName>
          <multipleReferencesAllowed>true</multipleReferencesAllowed>
        </featureDescription>
      </features>
    </typeDescription>
    <typeDescription>
      <name>rs.tf.StampedPose</name>
      <description>TF</description>
      <supertypeName>rs.tf.Pose</supertypeName>
      <features>
        <featureDescription>
          <name>frame</name>
          <description/>
          <rangeTypeName>uima.cas.String</rangeTypeName>
        </featureDescription>
        <featureDescription>
          <name>timestamp</name>
          <description/>
          <rangeTypeName>uima.cas.Long</rangeTypeName>
        </featureDescription>
      </features>
    </typeDescription>
    <typeDescription>
      <name>rs.tf.StampedTransform</name>
      <description>TF</description>
      <supertypeName>rs.tf.StampedPose</supertypeName>
      <features>
        <featureDescription>
          <name>childFrame</name>
          <description/>
          <rangeTypeName>uima.cas.String</rangeTypeName>
        </featureDescription>
      </features>
    </typeDescription>
  </types>
</typeSystemDescription>
